<?xml version="1.0" encoding="UTF-8"?><record_update sys_domain="global" table="sys_app_module">
    <sys_app_module action="DELETE">
        <active>true</active>
        <application/>
        <assessment/>
        <device_type/>
        <filter/>
        <hint/>
        <homepage/>
        <image/>
        <link_type>LIST</link_type>
        <map_page/>
        <mobile_title>List</mobile_title>
        <mobile_view_name>Mobile</mobile_view_name>
        <name>x_1421192_inventor_product_request</name>
        <order>200</order>
        <override_menu_roles>false</override_menu_roles>
        <query/>
        <report/>
        <require_confirmation>true</require_confirmation>
        <roles/>
        <sys_class_name>sys_app_module</sys_class_name>
        <sys_created_by>admin</sys_created_by>
        <sys_created_on>2024-06-13 02:28:07</sys_created_on>
        <sys_domain>global</sys_domain>
        <sys_domain_path>/</sys_domain_path>
        <sys_id>1e1364c593b6c2100d95b4697bba1037</sys_id>
        <sys_mod_count>0</sys_mod_count>
        <sys_name>List</sys_name>
        <sys_overrides/>
        <sys_package display_value="Inventory Management" source="x_1421192_inventor">2ef3dccd9336c2100d95b4697bba1023</sys_package>
        <sys_policy/>
        <sys_scope display_value="Inventory Management">2ef3dccd9336c2100d95b4697bba1023</sys_scope>
        <sys_update_name>sys_app_module_1e1364c593b6c2100d95b4697bba1037</sys_update_name>
        <sys_updated_by>admin</sys_updated_by>
        <sys_updated_on>2024-06-13 02:28:07</sys_updated_on>
        <timeline_page/>
        <title>List</title>
        <uncancelable>false</uncancelable>
        <view_name/>
        <window_name/>
    </sys_app_module>
    <sys_update_version action="INSERT_OR_UPDATE">
        <action>DELETE</action>
        <application display_value="Inventory Management">2ef3dccd9336c2100d95b4697bba1023</application>
        <file_path/>
        <instance_id>b8555d6e1b5efd147d9d2f8dee4bcbe0</instance_id>
        <instance_name>dev206780</instance_name>
        <name>sys_app_module_1e1364c593b6c2100d95b4697bba1037</name>
        <payload><![CDATA[<?xml version="1.0" encoding="UTF-8"?><record_update sys_domain="global" table="sys_app_module"><sys_app_module action="INSERT_OR_UPDATE"><active>true</active><application/><assessment/><device_type/><filter/><hint/><homepage/><image/><link_type>LIST</link_type><map_page/><mobile_title>List</mobile_title><mobile_view_name>Mobile</mobile_view_name><name>x_1421192_inventor_product_request</name><order>200</order><override_menu_roles>false</override_menu_roles><query/><report/><require_confirmation>true</require_confirmation><roles/><sys_class_name>sys_app_module</sys_class_name><sys_created_by>admin</sys_created_by><sys_created_on>2024-06-13 02:28:07</sys_created_on><sys_domain>global</sys_domain><sys_domain_path>/</sys_domain_path><sys_id>1e1364c593b6c2100d95b4697bba1037</sys_id><sys_mod_count>0</sys_mod_count><sys_name>List</sys_name><sys_overrides/><sys_package display_value="Inventory Management" source="x_1421192_inventor">2ef3dccd9336c2100d95b4697bba1023</sys_package><sys_policy/><sys_scope display_value="Inventory Management">2ef3dccd9336c2100d95b4697bba1023</sys_scope><sys_update_name>sys_app_module_1e1364c593b6c2100d95b4697bba1037</sys_update_name><sys_updated_by>admin</sys_updated_by><sys_updated_on>2024-06-13 02:28:07</sys_updated_on><timeline_page/><title>List</title><uncancelable>false</uncancelable><view_name/><window_name/></sys_app_module></record_update>]]></payload>
        <payload_hash>-1461576953</payload_hash>
        <record_name>List</record_name>
        <reverted_from/>
        <source>a2f3dccd9336c2100d95b4697bba1028</source>
        <source_table>sys_update_set</source_table>
        <state>previous</state>
        <sys_created_by>admin</sys_created_by>
        <sys_created_on>2024-06-13 17:27:42</sys_created_on>
        <sys_id>c711bb09933202100d95b4697bba1058</sys_id>
        <sys_mod_count>0</sys_mod_count>
        <sys_recorded_at>19012a419320000001</sys_recorded_at>
        <sys_updated_by>admin</sys_updated_by>
        <sys_updated_on>2024-06-13 17:27:42</sys_updated_on>
        <type>Module</type>
        <update_guid>e533acc5b2b6c2102618a8d645e7cf12</update_guid>
        <update_guid_history>e533acc5b2b6c2102618a8d645e7cf12:274851855,e533acc5b2b6c2102618a8d645e7cf12:274851855</update_guid_history>
    </sys_update_version>
    <sys_metadata_delete action="INSERT_OR_UPDATE">
        <sys_audit_delete display_value="List">bc313349933202100d95b4697bba10f6</sys_audit_delete>
        <sys_class_name>sys_metadata_delete</sys_class_name>
        <sys_created_by>admin</sys_created_by>
        <sys_created_on>2024-06-13 17:28:05</sys_created_on>
        <sys_db_object display_value="" name="sys_app_module">sys_app_module</sys_db_object>
        <sys_id>04609010e903428381090621e0b02201</sys_id>
        <sys_metadata>1e1364c593b6c2100d95b4697bba1037</sys_metadata>
        <sys_mod_count>0</sys_mod_count>
        <sys_name>List</sys_name>
        <sys_package display_value="Inventory Management" source="x_1421192_inventor">2ef3dccd9336c2100d95b4697bba1023</sys_package>
        <sys_parent/>
        <sys_policy/>
        <sys_scope display_value="Inventory Management">2ef3dccd9336c2100d95b4697bba1023</sys_scope>
        <sys_scope_delete display_value="">22c58d1ee1f942f8b2dfd373251ed2c4</sys_scope_delete>
        <sys_update_name>sys_app_module_1e1364c593b6c2100d95b4697bba1037</sys_update_name>
        <sys_update_version display_value="sys_app_module_1e1364c593b6c2100d95b4697bba1037">c711bb09933202100d95b4697bba1058</sys_update_version>
        <sys_updated_by>admin</sys_updated_by>
        <sys_updated_on>2024-06-13 17:28:05</sys_updated_on>
    </sys_metadata_delete>
</record_update>
